universalio/__init__.py
universalio/fileman.py
universalio/global_loop.py
universalio/batch/__init__.py
universalio/batch/batch.py
universalio/batch/sync.py
universalio/descriptors/__init__.py
universalio/descriptors/azure_blob.py
universalio/descriptors/base.py
universalio/descriptors/http.py
universalio/descriptors/local.py
universalio/descriptors/sftp.py
universalio/util/__init__.py
universalio-0.0.14.dist-info/LICENSE
universalio-0.0.14.dist-info/METADATA
universalio-0.0.14.dist-info/WHEEL
universalio-0.0.14.dist-info/top_level.txt
universalio-0.0.14.dist-info/RECORD
