Metadata-Version: 2.1
Name: universalio
Version: 0.0.14
Summary: Common API for asynchronous file management
Home-page: https://github.com/turnbullerin/universalio
Author: Erin Turnbull
Author-email: erin.a.turnbull@gmail.com
Project-URL: Bug Tracker, https://github.com/turnbullerin/universalio/issues
Classifier: Programming Language :: Python :: 3
Classifier: License :: OSI Approved :: MIT License
Classifier: Operating System :: OS Independent
Requires-Python: >=3.7
License-File: LICENSE
Requires-Dist: autoinject
Requires-Dist: zirconium (>=0.2)
Requires-Dist: toml
Requires-Dist: aiohttp
Requires-Dist: aiofiles
Requires-Dist: zrlog
Requires-Dist: importlib-metadata ; python_version < "3.8"
